{"MLP_run_1.pt": {"l1": 256, "l2": 64, "weight_decay": 1e-05, "batch_size": 64}, "MLP_run_2.pt": {"l1": 256, "l2": 64, "weight_decay": 1e-05, "batch_size": 128}, "MLP_run_3.pt": {"l1": 256, "l2": 64, "weight_decay": 0.0001, "batch_size": 64}, "MLP_run_4.pt": {"l1": 256, "l2": 64, "weight_decay": 0.0001, "batch_size": 128}, "MLP_run_5.pt": {"l1": 256, "l2": 32, "weight_decay": 1e-05, "batch_size": 64}, "MLP_run_6.pt": {"l1": 256, "l2": 32, "weight_decay": 1e-05, "batch_size": 128}, "MLP_run_7.pt": {"l1": 256, "l2": 32, "weight_decay": 0.0001, "batch_size": 64}, "MLP_run_8.pt": {"l1": 256, "l2": 32, "weight_decay": 0.0001, "batch_size": 128}, "MLP_run_9.pt": {"l1": 128, "l2": 64, "weight_decay": 1e-05, "batch_size": 64}, "MLP_run_10.pt": {"l1": 128, "l2": 64, "weight_decay": 1e-05, "batch_size": 128}, "MLP_run_11.pt": {"l1": 128, "l2": 64, "weight_decay": 0.0001, "batch_size": 64}, "MLP_run_12.pt": {"l1": 128, "l2": 64, "weight_decay": 0.0001, "batch_size": 128}, "MLP_run_13.pt": {"l1": 128, "l2": 32, "weight_decay": 1e-05, "batch_size": 64}, "MLP_run_14.pt": {"l1": 128, "l2": 32, "weight_decay": 1e-05, "batch_size": 128}, "MLP_run_15.pt": {"l1": 128, "l2": 32, "weight_decay": 0.0001, "batch_size": 64}, "MLP_run_16.pt": {"l1": 128, "l2": 32, "weight_decay": 0.0001, "batch_size": 128}}